src/__init__.py
src/cli.py
src/main.py
src/pdf.py
img_to_pdf-1.0.2.dist-info/LICENSE
img_to_pdf-1.0.2.dist-info/METADATA
img_to_pdf-1.0.2.dist-info/WHEEL
img_to_pdf-1.0.2.dist-info/entry_points.txt
img_to_pdf-1.0.2.dist-info/top_level.txt
img_to_pdf-1.0.2.dist-info/RECORD
