Metadata-Version: 2.1
Name: img-to-pdf
Version: 1.0.2
Summary: Simple CLI tool to convert images in a directory to a PDF
Home-page: https://github.com/Cbannon35/makePDF
Author: Christopher Bannon
Author-email: cbannon@berkeley.edu
License: MIT
Keywords: PDF,image,convert
License-File: LICENSE
Requires-Dist: img2pdf ==0.5.1
Requires-Dist: Pillow ==10.2.0
Requires-Dist: pillow-heif ==0.15.0
Requires-Dist: PyPDF2 ==3.0.1
Requires-Dist: setuptools ==58.0.4
Requires-Dist: tqdm ==4.62.3
